dictionary/__init__.py
dictionary/dictionary.py
iremtekin_dictionary-2.0.0.dist-info/METADATA
iremtekin_dictionary-2.0.0.dist-info/WHEEL
iremtekin_dictionary-2.0.0.dist-info/top_level.txt
iremtekin_dictionary-2.0.0.dist-info/RECORD
